harmony/__init__.py
harmony/__main__.py
harmony/config.py
harmony/discord.py
harmony/harmony.py
harmony/keyring.py
harmony/messages.py
harmony/user_agent_data.py
harmony/user_agents.py
harmony_discord-0.7.2.dist-info/LICENSE
harmony_discord-0.7.2.dist-info/METADATA
harmony_discord-0.7.2.dist-info/WHEEL
harmony_discord-0.7.2.dist-info/entry_points.txt
harmony_discord-0.7.2.dist-info/top_level.txt
harmony_discord-0.7.2.dist-info/RECORD
